usbhubctl-0.0.1.dist-info/METADATA
usbhubctl-0.0.1.dist-info/WHEEL
usbhubctl-0.0.1.dist-info/licenses/LICENSE
usbhubctl/README_usbhub.md
usbhubctl/__init__.py
usbhubctl/backend_power_sysfs.py
usbhubctl/backend_power_uhubctl.py
usbhubctl/backend_query_lsusb.py
usbhubctl/known_hubs/__init__.py
usbhubctl/known_hubs/rsh_a10.py
usbhubctl/known_hubs/rsh_a107.py
usbhubctl/known_hubs/rsh_a16.py
usbhubctl/known_hubs/rsh_st07c.py
usbhubctl/parser_lsusb.py
usbhubctl/sample_pyusb_usbhub.py
usbhubctl/sample_pyusb_usbhub_container.py
usbhubctl/sample_pyusb_usbhub_simple.py
usbhubctl/sample_pyusb_usbhub_simple_bak.py
usbhubctl/usbhubctl.py
usbhubctl/util_logging.json
usbhubctl/util_logging.py
usbhubctl/util_subprocess.py
usbhubctl-0.0.1.dist-info/RECORD
