Metadata-Version: 2.1
Name: usbhubctl
Version: 0.0.1
Summary: Allows to switch power on usb hubs
Author-Email: =?utf-8?q?Hans_M=C3=A4rki?= <buhtig.hans.maerki@ergoinfo.ch>
Classifier: Intended Audience :: Information Technology
Classifier: Operating System :: POSIX :: Linux
Classifier: Programming Language :: Python :: 3.13
Classifier: Programming Language :: Python :: 3.12
Classifier: Programming Language :: Python
Classifier: Topic :: Software Development :: Libraries
Classifier: Topic :: Software Development
Classifier: Typing :: Typed
Classifier: Development Status :: 4 - Beta
Classifier: Intended Audience :: Developers
Classifier: Intended Audience :: System Administrators
Classifier: License :: OSI Approved :: MIT License
Project-URL: Homepage, https://github.com/octoprobe/usbhubctl
Project-URL: Documentation, https://github.com/octoprobe/usbhubctl
Project-URL: Repository, https://github.com/octoprobe/usbhubctl
Requires-Python: >=3.8
Provides-Extra: standard
Provides-Extra: all
